{"location": {"name": "Lublin", "region": "", "country": "Poland", "lat": 51.25, "lon": 22.57, "tz_id": "Europe/Warsaw", "localtime_epoch": 1615918345, "localtime": "2021-03-16 19:12"}, "forecast": {"forecastday": [{"date": "2017-10-21", "date_epoch": 1508544000, "day": {"maxtemp_c": 14.2, "maxtemp_f": 57.6, "mintemp_c": 8.5, "mintemp_f": 47.3, "avgtemp_c": 11.7, "avgtemp_f": 53.0, "maxwind_mph": 6.7, "maxwind_kph": 10.8, "totalprecip_mm": 0.2, "totalprecip_in": 0.01, "avgvis_km": 9.0, "avgvis_miles": 5.0, "avghumidity": 85.0, "condition": {"text": "Cloudy", "icon": "//cdn.weatherapi.com/weather/64x64/day/119.png", "code": 1006}, "uv": 0.0}, "astro": {"sunrise": "06:04 AM", "sunset": "04:24 PM", "moonrise": "07:26 AM", "moonset": "05:38 PM", "moon_phase": "Waxing Crescent", "moon_illumination": "3"}, "hour": [{"time_epoch": 1508536800, "time": "2017-10-21 00:00", "temp_c": 9.0, "temp_f": 48.2, "is_day": 0, "condition": {"text": "Clear", "icon": "//cdn.weatherapi.com/weather/64x64/night/113.png", "code": 1000}, "wind_mph": 4.0, "wind_kph": 6.5, "wind_degree": 169, "wind_dir": "S", "pressure_mb": 1018.0, "pressure_in": 30.5, "precip_mm": 0.0, "precip_in": 0.0, "humidity": 93, "cloud": 7, "feelslike_c": 8.0, "feelslike_f": 46.4, "windchill_c": 8.0, "windchill_f": 46.4, "heatindex_c": 9.0, "heatindex_f": 48.2, "dewpoint_c": 7.9, "dewpoint_f": 46.2, "will_it_rain": 0, "chance_of_rain": "0", "will_it_snow": 0, "chance_of_snow": "0", "vis_km": 10.0, "vis_miles": 6.0, "gust_mph": 8.2, "gust_kph": 13.2}, {"time_epoch": 1508540400, "time": "2017-10-21 01:00", "temp_c": 8.8, "temp_f": 47.9, "is_day": 0, "condition": {"text": "Clear", "icon": "//cdn.weatherapi.com/weather/64x64/night/113.png", "code": 1000}, "wind_mph": 4.2, "wind_kph": 6.7, "wind_degree": 174, "wind_dir": "S", "pressure_mb": 1017.0, "pressure_in": 30.5, "precip_mm": 0.0, "precip_in": 0.0, "humidity": 93, "cloud": 16, "feelslike_c": 7.8, "feelslike_f": 46.0, "windchill_c": 7.8, "windchill_f": 46.0, "heatindex_c": 8.8, "heatindex_f": 47.9, "dewpoint_c": 7.8, "dewpoint_f": 46.0, "will_it_rain": 0, "chance_of_rain": "0", "will_it_snow": 0, "chance_of_snow": "0", "vis_km": 10.0, "vis_miles": 6.0, "gust_mph": 8.5, "gust_kph": 13.7}, {"time_epoch": 1508544000, "time": "2017-10-21 02:00", "temp_c": 8.7, "temp_f": 47.6, "is_day": 0, "condition": {"text": "Partly cloudy", "icon": "//cdn.weatherapi.com/weather/64x64/night/116.png", "code": 1003}, "wind_mph": 4.3, "wind_kph": 7.0, "wind_degree": 180, "wind_dir": "S", "pressure_mb": 1017.0, "pressure_in": 30.5, "precip_mm": 0.0, "precip_in": 0.0, "humidity": 93, "cloud": 26, "feelslike_c": 7.6, "feelslike_f": 45.7, "windchill_c": 7.6, "windchill_f": 45.7, "heatindex_c": 8.7, "heatindex_f": 47.6, "dewpoint_c": 7.6, "dewpoint_f": 45.7, "will_it_rain": 0, "chance_of_rain": "1", "will_it_snow": 0, "chance_of_snow": "0", "vis_km": 10.0, "vis_miles": 6.0, "gust_mph": 8.8, "gust_kph": 14.2}, {"time_epoch": 1508547600, "time": "2017-10-21 03:00", "temp_c": 8.5, "temp_f": 47.3, "is_day": 0, "condition": {"text": "Partly cloudy", "icon": "//cdn.weatherapi.com/weather/64x64/night/116.png", "code": 1003}, "wind_mph": 4.5, "wind_kph": 7.2, "wind_degree": 186, "wind_dir": "S", "pressure_mb": 1017.0, "pressure_in": 30.5, "precip_mm": 0.0, "precip_in": 0.0, "humidity": 93, "cloud": 35, "feelslike_c": 7.4, "feelslike_f": 45.3, "windchill_c": 7.4, "windchill_f": 45.3, "heatindex_c": 8.5, "heatindex_f": 47.3, "dewpoint_c": 7.5, "dewpoint_f": 45.5, "will_it_rain": 0, "chance_of_rain": "0", "will_it_snow": 0, "chance_of_snow": "0", "vis_km": 10.0, "vis_miles": 6.0, "gust_mph": 9.1, "gust_kph": 14.7}, {"time_epoch": 1508551200, "time": "2017-10-21 04:00", "temp_c": 8.7, "temp_f": 47.6, "is_day": 0, "condition": {"text": "Partly cloudy", "icon": "//cdn.weatherapi.com/weather/64x64/night/116.png", "code": 1003}, "wind_mph": 4.1, "wind_kph": 6.6, "wind_degree": 191, "wind_dir": "SSW", "pressure_mb": 1016.0, "pressure_in": 30.5, "precip_mm": 0.0, "precip_in": 0.0, "humidity": 92, "cloud": 48, "feelslike_c": 7.5, "feelslike_f": 45.6, "windchill_c": 7.5, "windchill_f": 45.6, "heatindex_c": 8.7, "heatindex_f": 47.6, "dewpoint_c": 7.5, "dewpoint_f": 45.5, "will_it_rain": 0, "chance_of_rain": "1", "will_it_snow": 0, "chance_of_snow": "0", "vis_km": 10.0, "vis_miles": 6.0, "gust_mph": 7.9, "gust_kph": 12.7}, {"time_epoch": 1508554800, "time": "2017-10-21 05:00", "temp_c": 8.8, "temp_f": 47.9, "is_day": 0, "condition": {"text": "Cloudy", "icon": "//cdn.weatherapi.com/weather/64x64/night/119.png", "code": 1006}, "wind_mph": 3.7, "wind_kph": 6.0, "wind_degree": 196, "wind_dir": "SSW", "pressure_mb": 1016.0, "pressure_in": 30.5, "precip_mm": 0.0, "precip_in": 0.0, "humidity": 91, "cloud": 61, "feelslike_c": 7.7, "feelslike_f": 45.8, "windchill_c": 7.7, "windchill_f": 45.8, "heatindex_c": 8.8, "heatindex_f": 47.9, "dewpoint_c": 7.5, "dewpoint_f": 45.5, "will_it_rain": 0, "chance_of_rain": "2", "will_it_snow": 0, "chance_of_snow": "0", "vis_km": 10.0, "vis_miles": 6.0, "gust_mph": 6.7, "gust_kph": 10.8}, {"time_epoch": 1508558400, "time": "2017-10-21 06:00", "temp_c": 9.0, "temp_f": 48.2, "is_day": 0, "condition": {"text": "Cloudy", "icon": "//cdn.weatherapi.com/weather/64x64/night/119.png", "code": 1006}, "wind_mph": 3.4, "wind_kph": 5.4, "wind_degree": 202, "wind_dir": "SSW", "pressure_mb": 1016.0, "pressure_in": 30.5, "precip_mm": 0.0, "precip_in": 0.0, "humidity": 91, "cloud": 74, "feelslike_c": 7.8, "feelslike_f": 46.0, "windchill_c": 7.8, "windchill_f": 46.0, "heatindex_c": 9.0, "heatindex_f": 48.2, "dewpoint_c": 7.5, "dewpoint_f": 45.5, "will_it_rain": 0, "chance_of_rain": "0", "will_it_snow": 0, "chance_of_snow": "0", "vis_km": 10.0, "vis_miles": 6.0, "gust_mph": 5.5, "gust_kph": 8.9}, {"time_epoch": 1508562000, "time": "2017-10-21 07:00", "temp_c": 10.2, "temp_f": 50.4, "is_day": 1, "condition": {"text": "Cloudy", "icon": "//cdn.weatherapi.com/weather/64x64/day/119.png", "code": 1006}, "wind_mph": 4.0, "wind_kph": 6.5, "wind_degree": 216, "wind_dir": "SW", "pressure_mb": 1016.0, "pressure_in": 30.5, "precip_mm": 0.0, "precip_in": 0.0, "humidity": 85, "cloud": 57, "feelslike_c": 9.2, "feelslike_f": 48.6, "windchill_c": 9.2, "windchill_f": 48.6, "heatindex_c": 10.2, "heatindex_f": 50.4, "dewpoint_c": 7.8, "dewpoint_f": 46.0, "will_it_rain": 0, "chance_of_rain": "2", "will_it_snow": 0, "chance_of_snow": "0", "vis_km": 10.0, "vis_miles": 6.0, "gust_mph": 5.7, "gust_kph": 9.2}, {"time_epoch": 1508565600, "time": "2017-10-21 08:00", "temp_c": 11.5, "temp_f": 52.6, "is_day": 1, "condition": {"text": "Sunny", "icon": "//cdn.weatherapi.com/weather/64x64/day/113.png", "code": 1000}, "wind_mph": 4.7, "wind_kph": 7.6, "wind_degree": 231, "wind_dir": "SW", "pressure_mb": 1015.0, "pressure_in": 30.5, "precip_mm": 0.0, "precip_in": 0.0, "humidity": 80, "cloud": 41, "feelslike_c": 10.7, "feelslike_f": 51.2, "windchill_c": 10.7, "windchill_f": 51.2, "heatindex_c": 11.5, "heatindex_f": 52.6, "dewpoint_c": 8.0, "dewpoint_f": 46.5, "will_it_rain": 0, "chance_of_rain": "0", "will_it_snow": 0, "chance_of_snow": "0", "vis_km": 10.0, "vis_miles": 6.0, "gust_mph": 6.0, "gust_kph": 9.6}, {"time_epoch": 1508569200, "time": "2017-10-21 09:00", "temp_c": 12.7, "temp_f": 54.9, "is_day": 1, "condition": {"text": "Sunny", "icon": "//cdn.weatherapi.com/weather/64x64/day/113.png", "code": 1000}, "wind_mph": 5.4, "wind_kph": 8.6, "wind_degree": 246, "wind_dir": "WSW", "pressure_mb": 1015.0, "pressure_in": 30.5, "precip_mm": 0.0, "precip_in": 0.0, "humidity": 75, "cloud": 24, "feelslike_c": 12.1, "feelslike_f": 53.8, "windchill_c": 12.1, "windchill_f": 53.8, "heatindex_c": 12.7, "heatindex_f": 54.9, "dewpoint_c": 8.3, "dewpoint_f": 46.9, "will_it_rain": 0, "chance_of_rain": "0", "will_it_snow": 0, "chance_of_snow": "0", "vis_km": 10.0, "vis_miles": 6.0, "gust_mph": 6.2, "gust_kph": 10.0}, {"time_epoch": 1508572800, "time": "2017-10-21 10:00", "temp_c": 13.2, "temp_f": 55.8, "is_day": 1, "condition": {"text": "Sunny", "icon": "//cdn.weatherapi.com/weather/64x64/day/113.png", "code": 1000}, "wind_mph": 5.8, "wind_kph": 9.4, "wind_degree": 251, "wind_dir": "WSW", "pressure_mb": 1015.0, "pressure_in": 30.4, "precip_mm": 0.0, "precip_in": 0.0, "humidity": 72, "cloud": 23, "feelslike_c": 12.6, "feelslike_f": 54.6, "windchill_c": 12.6, "windchill_f": 54.6, "heatindex_c": 13.2, "heatindex_f": 55.8, "dewpoint_c": 8.3, "dewpoint_f": 46.9, "will_it_rain": 0, "chance_of_rain": "0", "will_it_snow": 0, "chance_of_snow": "0", "vis_km": 10.0, "vis_miles": 6.0, "gust_mph": 6.7, "gust_kph": 10.8}, {"time_epoch": 1508576400, "time": "2017-10-21 11:00", "temp_c": 13.7, "temp_f": 56.7, "is_day": 1, "condition": {"text": "Sunny", "icon": "//cdn.weatherapi.com/weather/64x64/day/113.png", "code": 1000}, "wind_mph": 6.3, "wind_kph": 10.1, "wind_degree": 256, "wind_dir": "WSW", "pressure_mb": 1014.0, "pressure_in": 30.4, "precip_mm": 0.0, "precip_in": 0.0, "humidity": 70, "cloud": 22, "feelslike_c": 13.0, "feelslike_f": 55.5, "windchill_c": 13.0, "windchill_f": 55.5, "heatindex_c": 13.7, "heatindex_f": 56.7, "dewpoint_c": 8.2, "dewpoint_f": 46.8, "will_it_rain": 0, "chance_of_rain": "0", "will_it_snow": 0, "chance_of_snow": "0", "vis_km": 10.0, "vis_miles": 6.0, "gust_mph": 7.2, "gust_kph": 11.6}, {"time_epoch": 1508580000, "time": "2017-10-21 12:00", "temp_c": 14.2, "temp_f": 57.6, "is_day": 1, "condition": {"text": "Sunny", "icon": "//cdn.weatherapi.com/weather/64x64/day/113.png", "code": 1000}, "wind_mph": 6.7, "wind_kph": 10.8, "wind_degree": 262, "wind_dir": "W", "pressure_mb": 1014.0, "pressure_in": 30.4, "precip_mm": 0.0, "precip_in": 0.0, "humidity": 67, "cloud": 20, "feelslike_c": 13.5, "feelslike_f": 56.3, "windchill_c": 13.5, "windchill_f": 56.3, "heatindex_c": 14.2, "heatindex_f": 57.6, "dewpoint_c": 8.2, "dewpoint_f": 46.8, "will_it_rain": 0, "chance_of_rain": "0", "will_it_snow": 0, "chance_of_snow": "0", "vis_km": 10.0, "vis_miles": 6.0, "gust_mph": 7.7, "gust_kph": 12.5}, {"time_epoch": 1508583600, "time": "2017-10-21 13:00", "temp_c": 13.7, "temp_f": 56.6, "is_day": 1, "condition": {"text": "Sunny", "icon": "//cdn.weatherapi.com/weather/64x64/day/113.png", "code": 1000}, "wind_mph": 6.0, "wind_kph": 9.7, "wind_degree": 276, "wind_dir": "W", "pressure_mb": 1014.0, "pressure_in": 30.4, "precip_mm": 0.0, "precip_in": 0.0, "humidity": 70, "cloud": 27, "feelslike_c": 13.0, "feelslike_f": 55.5, "windchill_c": 13.0, "windchill_f": 55.5, "heatindex_c": 13.7, "heatindex_f": 56.6, "dewpoint_c": 8.2, "dewpoint_f": 46.8, "will_it_rain": 0, "chance_of_rain": "0", "will_it_snow": 0, "chance_of_snow": "0", "vis_km": 10.0, "vis_miles": 6.0, "gust_mph": 7.6, "gust_kph": 12.2}, {"time_epoch": 1508587200, "time": "2017-10-21 14:00", "temp_c": 13.1, "temp_f": 55.6, "is_day": 1, "condition": {"text": "Partly cloudy", "icon": "//cdn.weatherapi.com/weather/64x64/day/116.png", "code": 1003}, "wind_mph": 5.4, "wind_kph": 8.6, "wind_degree": 291, "wind_dir": "WNW", "pressure_mb": 1014.0, "pressure_in": 30.4, "precip_mm": 0.03, "precip_in": 0.0, "humidity": 72, "cloud": 35, "feelslike_c": 12.6, "feelslike_f": 54.6, "windchill_c": 12.6, "windchill_f": 54.6, "heatindex_c": 13.1, "heatindex_f": 55.6, "dewpoint_c": 8.3, "dewpoint_f": 46.9, "will_it_rain": 0, "chance_of_rain": "1", "will_it_snow": 0, "chance_of_snow": "0", "vis_km": 10.0, "vis_miles": 6.0, "gust_mph": 7.4, "gust_kph": 12.0}, {"time_epoch": 1508590800, "time": "2017-10-21 15:00", "temp_c": 12.6, "temp_f": 54.7, "is_day": 1, "condition": {"text": "Partly cloudy", "icon": "//cdn.weatherapi.com/weather/64x64/day/116.png", "code": 1003}, "wind_mph": 4.7, "wind_kph": 7.6, "wind_degree": 306, "wind_dir": "NW", "pressure_mb": 1014.0, "pressure_in": 30.4, "precip_mm": 0.04, "precip_in": 0.0, "humidity": 75, "cloud": 42, "feelslike_c": 12.1, "feelslike_f": 53.8, "windchill_c": 12.1, "windchill_f": 53.8, "heatindex_c": 12.6, "heatindex_f": 54.7, "dewpoint_c": 8.3, "dewpoint_f": 46.9, "will_it_rain": 0, "chance_of_rain": "0", "will_it_snow": 0, "chance_of_snow": "0", "vis_km": 10.0, "vis_miles": 6.0, "gust_mph": 7.3, "gust_kph": 11.7}, {"time_epoch": 1508594400, "time": "2017-10-21 16:00", "temp_c": 11.7, "temp_f": 53.0, "is_day": 1, "condition": {"text": "Partly cloudy", "icon": "//cdn.weatherapi.com/weather/64x64/day/116.png", "code": 1003}, "wind_mph": 4.8, "wind_kph": 7.8, "wind_degree": 319, "wind_dir": "NW", "pressure_mb": 1014.0, "pressure_in": 30.4, "precip_mm": 0.02, "precip_in": 0.0, "humidity": 80, "cloud": 51, "feelslike_c": 11.1, "feelslike_f": 52.0, "windchill_c": 11.1, "windchill_f": 52.0, "heatindex_c": 11.7, "heatindex_f": 53.0, "dewpoint_c": 8.3, "dewpoint_f": 46.9, "will_it_rain": 0, "chance_of_rain": "1", "will_it_snow": 0, "chance_of_snow": "0", "vis_km": 10.0, "vis_miles": 6.0, "gust_mph": 8.1, "gust_kph": 13.0}, {"time_epoch": 1508598000, "time": "2017-10-21 17:00", "temp_c": 10.7, "temp_f": 51.3, "is_day": 0, "condition": {"text": "Cloudy", "icon": "//cdn.weatherapi.com/weather/64x64/night/119.png", "code": 1006}, "wind_mph": 5.0, "wind_kph": 8.0, "wind_degree": 332, "wind_dir": "NNW", "pressure_mb": 1015.0, "pressure_in": 30.4, "precip_mm": 0.03, "precip_in": 0.0, "humidity": 85, "cloud": 61, "feelslike_c": 10.1, "feelslike_f": 50.2, "windchill_c": 10.1, "windchill_f": 50.2, "heatindex_c": 10.7, "heatindex_f": 51.3, "dewpoint_c": 8.2, "dewpoint_f": 46.8, "will_it_rain": 0, "chance_of_rain": "2", "will_it_snow": 0, "chance_of_snow": "0", "vis_km": 10.0, "vis_miles": 6.0, "gust_mph": 8.8, "gust_kph": 14.2}, {"time_epoch": 1508601600, "time": "2017-10-21 18:00", "temp_c": 9.8, "temp_f": 49.6, "is_day": 0, "condition": {"text": "Cloudy", "icon": "//cdn.weatherapi.com/weather/64x64/night/119.png", "code": 1006}, "wind_mph": 5.1, "wind_kph": 8.3, "wind_degree": 345, "wind_dir": "NNW", "pressure_mb": 1015.0, "pressure_in": 30.5, "precip_mm": 0.04, "precip_in": 0.0, "humidity": 90, "cloud": 71, "feelslike_c": 9.1, "feelslike_f": 48.4, "windchill_c": 9.1, "windchill_f": 48.4, "heatindex_c": 9.8, "heatindex_f": 49.6, "dewpoint_c": 8.2, "dewpoint_f": 46.8, "will_it_rain": 0, "chance_of_rain": "0", "will_it_snow": 0, "chance_of_snow": "0", "vis_km": 10.0, "vis_miles": 6.0, "gust_mph": 9.6, "gust_kph": 15.4}, {"time_epoch": 1508605200, "time": "2017-10-21 19:00", "temp_c": 9.4, "temp_f": 48.9, "is_day": 0, "condition": {"text": "Cloudy", "icon": "//cdn.weatherapi.com/weather/64x64/night/119.png", "code": 1006}, "wind_mph": 4.6, "wind_kph": 7.4, "wind_degree": 233, "wind_dir": "SW", "pressure_mb": 1016.0, "pressure_in": 30.5, "precip_mm": 0.02, "precip_in": 0.0, "humidity": 92, "cloud": 75, "feelslike_c": 8.7, "feelslike_f": 47.7, "windchill_c": 8.7, "windchill_f": 47.7, "heatindex_c": 9.4, "heatindex_f": 48.9, "dewpoint_c": 8.1, "dewpoint_f": 46.6, "will_it_rain": 0, "chance_of_rain": "2", "will_it_snow": 0, "chance_of_snow": "0", "vis_km": 7.3, "vis_miles": 4.0, "gust_mph": 8.6, "gust_kph": 13.8}, {"time_epoch": 1508608800, "time": "2017-10-21 20:00", "temp_c": 9.0, "temp_f": 48.2, "is_day": 0, "condition": {"text": "Mist", "icon": "//cdn.weatherapi.com/weather/64x64/night/143.png", "code": 1030}, "wind_mph": 4.1, "wind_kph": 6.6, "wind_degree": 121, "wind_dir": "ESE", "pressure_mb": 1016.0, "pressure_in": 30.5, "precip_mm": 0.0, "precip_in": 0.0, "humidity": 94, "cloud": 79, "feelslike_c": 8.3, "feelslike_f": 46.9, "windchill_c": 8.3, "windchill_f": 46.9, "heatindex_c": 9.0, "heatindex_f": 48.2, "dewpoint_c": 8.0, "dewpoint_f": 46.4, "will_it_rain": 0, "chance_of_rain": "10", "will_it_snow": 0, "chance_of_snow": "0", "vis_km": 4.7, "vis_miles": 2.0, "gust_mph": 7.6, "gust_kph": 12.2}, {"time_epoch": 1508612400, "time": "2017-10-21 21:00", "temp_c": 8.6, "temp_f": 47.5, "is_day": 0, "condition": {"text": "Mist", "icon": "//cdn.weatherapi.com/weather/64x64/night/143.png", "code": 1030}, "wind_mph": 3.6, "wind_kph": 5.8, "wind_degree": 10, "wind_dir": "N", "pressure_mb": 1016.0, "pressure_in": 30.5, "precip_mm": 0.0, "precip_in": 0.0, "humidity": 95, "cloud": 84, "feelslike_c": 7.9, "feelslike_f": 46.2, "windchill_c": 7.9, "windchill_f": 46.2, "heatindex_c": 8.6, "heatindex_f": 47.5, "dewpoint_c": 7.9, "dewpoint_f": 46.2, "will_it_rain": 0, "chance_of_rain": "0", "will_it_snow": 0, "chance_of_snow": "0", "vis_km": 2.0, "vis_miles": 1.0, "gust_mph": 6.6, "gust_kph": 10.6}, {"time_epoch": 1508616000, "time": "2017-10-21 22:00", "temp_c": 8.7, "temp_f": 47.6, "is_day": 0, "condition": {"text": "Mist", "icon": "//cdn.weatherapi.com/weather/64x64/night/143.png", "code": 1030}, "wind_mph": 3.6, "wind_kph": 5.8, "wind_degree": 26, "wind_dir": "NNE", "pressure_mb": 1017.0, "pressure_in": 30.5, "precip_mm": 0.0, "precip_in": 0.0, "humidity": 95, "cloud": 89, "feelslike_c": 8.0, "feelslike_f": 46.4, "windchill_c": 8.0, "windchill_f": 46.4, "heatindex_c": 8.7, "heatindex_f": 47.6, "dewpoint_c": 7.9, "dewpoint_f": 46.3, "will_it_rain": 0, "chance_of_rain": "10", "will_it_snow": 0, "chance_of_snow": "0", "vis_km": 2.0, "vis_miles": 1.0, "gust_mph": 6.3, "gust_kph": 10.1}, {"time_epoch": 1508619600, "time": "2017-10-21 23:00", "temp_c": 8.7, "temp_f": 47.7, "is_day": 0, "condition": {"text": "Mist", "icon": "//cdn.weatherapi.com/weather/64x64/night/143.png", "code": 1030}, "wind_mph": 3.6, "wind_kph": 5.8, "wind_degree": 42, "wind_dir": "NE", "pressure_mb": 1017.0, "pressure_in": 30.5, "precip_mm": 0.0, "precip_in": 0.0, "humidity": 95, "cloud": 95, "feelslike_c": 8.1, "feelslike_f": 46.6, "windchill_c": 8.1, "windchill_f": 46.6, "heatindex_c": 8.7, "heatindex_f": 47.7, "dewpoint_c": 8.0, "dewpoint_f": 46.3, "will_it_rain": 0, "chance_of_rain": "10", "will_it_snow": 0, "chance_of_snow": "0", "vis_km": 2.0, "vis_miles": 1.0, "gust_mph": 6.0, "gust_kph": 9.6}]}]}}