{"location": {"name": "Krotoszyn", "region": "", "country": "Poland", "lat": 51.7, "lon": 17.45, "tz_id": "Europe/Warsaw", "localtime_epoch": 1615921614, "localtime": "2021-03-16 20:06"}, "forecast": {"forecastday": [{"date": "2019-12-11", "date_epoch": 1576022400, "day": {"maxtemp_c": 3.3, "maxtemp_f": 37.9, "mintemp_c": -0.5, "mintemp_f": 31.1, "avgtemp_c": 1.0, "avgtemp_f": 33.8, "maxwind_mph": 12.3, "maxwind_kph": 19.8, "totalprecip_mm": 0.0, "totalprecip_in": 0.0, "avgvis_km": 10.0, "avgvis_miles": 6.0, "avghumidity": 67.0, "condition": {"text": "Sunny", "icon": "//cdn.weatherapi.com/weather/64x64/day/113.png", "code": 1000}, "uv": 0.0}, "astro": {"sunrise": "07:46 AM", "sunset": "03:40 PM", "moonrise": "03:25 PM", "moonset": "06:34 AM", "moon_phase": "Waxing Gibbous", "moon_illumination": "99"}, "hour": [{"time_epoch": 1576018800, "time": "2019-12-11 00:00", "temp_c": 0.5, "temp_f": 32.9, "is_day": 0, "condition": {"text": "Clear", "icon": "//cdn.weatherapi.com/weather/64x64/night/113.png", "code": 1000}, "wind_mph": 4.7, "wind_kph": 7.6, "wind_degree": 263, "wind_dir": "W", "pressure_mb": 1025.0, "pressure_in": 30.7, "precip_mm": 0.0, "precip_in": 0.0, "humidity": 92, "cloud": 13, "feelslike_c": -1.6, "feelslike_f": 29.1, "windchill_c": -1.6, "windchill_f": 29.1, "heatindex_c": 0.5, "heatindex_f": 32.9, "dewpoint_c": -0.6, "dewpoint_f": 30.9, "will_it_rain": 0, "chance_of_rain": "0", "will_it_snow": 0, "chance_of_snow": "0", "vis_km": 10.0, "vis_miles": 6.0, "gust_mph": 6.7, "gust_kph": 10.8}, {"time_epoch": 1576022400, "time": "2019-12-11 01:00", "temp_c": 0.3, "temp_f": 32.5, "is_day": 0, "condition": {"text": "Clear", "icon": "//cdn.weatherapi.com/weather/64x64/night/113.png", "code": 1000}, "wind_mph": 4.6, "wind_kph": 7.4, "wind_degree": 242, "wind_dir": "WSW", "pressure_mb": 1024.0, "pressure_in": 30.7, "precip_mm": 0.0, "precip_in": 0.0, "humidity": 91, "cloud": 12, "feelslike_c": -2.5, "feelslike_f": 27.5, "windchill_c": -2.5, "windchill_f": 27.5, "heatindex_c": 0.3, "heatindex_f": 32.5, "dewpoint_c": -1.0, "dewpoint_f": 30.3, "will_it_rain": 0, "chance_of_rain": "0", "will_it_snow": 0, "chance_of_snow": "0", "vis_km": 10.0, "vis_miles": 6.0, "gust_mph": 6.6, "gust_kph": 10.6}, {"time_epoch": 1576026000, "time": "2019-12-11 02:00", "temp_c": 0.0, "temp_f": 32.1, "is_day": 0, "condition": {"text": "Clear", "icon": "//cdn.weatherapi.com/weather/64x64/night/113.png", "code": 1000}, "wind_mph": 4.5, "wind_kph": 7.3, "wind_degree": 220, "wind_dir": "SW", "pressure_mb": 1023.0, "pressure_in": 30.7, "precip_mm": 0.0, "precip_in": 0.0, "humidity": 90, "cloud": 10, "feelslike_c": -3.4, "feelslike_f": 25.9, "windchill_c": -3.4, "windchill_f": 25.9, "heatindex_c": 0.0, "heatindex_f": 32.1, "dewpoint_c": -1.3, "dewpoint_f": 29.6, "will_it_rain": 0, "chance_of_rain": "0", "will_it_snow": 0, "chance_of_snow": "0", "vis_km": 10.0, "vis_miles": 6.0, "gust_mph": 6.4, "gust_kph": 10.3}, {"time_epoch": 1576029600, "time": "2019-12-11 03:00", "temp_c": -0.2, "temp_f": 31.6, "is_day": 0, "condition": {"text": "Clear", "icon": "//cdn.weatherapi.com/weather/64x64/night/113.png", "code": 1000}, "wind_mph": 4.5, "wind_kph": 7.2, "wind_degree": 198, "wind_dir": "SSW", "pressure_mb": 1022.0, "pressure_in": 30.7, "precip_mm": 0.0, "precip_in": 0.0, "humidity": 89, "cloud": 8, "feelslike_c": -4.3, "feelslike_f": 24.3, "windchill_c": -4.3, "windchill_f": 24.3, "heatindex_c": -0.2, "heatindex_f": 31.6, "dewpoint_c": -1.7, "dewpoint_f": 28.9, "will_it_rain": 0, "chance_of_rain": "0", "will_it_snow": 0, "chance_of_snow": "0", "vis_km": 10.0, "vis_miles": 6.0, "gust_mph": 6.3, "gust_kph": 10.1}, {"time_epoch": 1576033200, "time": "2019-12-11 04:00", "temp_c": -0.2, "temp_f": 31.7, "is_day": 0, "condition": {"text": "Clear", "icon": "//cdn.weatherapi.com/weather/64x64/night/113.png", "code": 1000}, "wind_mph": 5.4, "wind_kph": 8.8, "wind_degree": 188, "wind_dir": "S", "pressure_mb": 1022.0, "pressure_in": 30.7, "precip_mm": 0.0, "precip_in": 0.0, "humidity": 86, "cloud": 6, "feelslike_c": -4.5, "feelslike_f": 23.8, "windchill_c": -4.5, "windchill_f": 23.8, "heatindex_c": -0.2, "heatindex_f": 31.7, "dewpoint_c": -2.2, "dewpoint_f": 28.0, "will_it_rain": 0, "chance_of_rain": "0", "will_it_snow": 0, "chance_of_snow": "0", "vis_km": 10.0, "vis_miles": 6.0, "gust_mph": 8.3, "gust_kph": 13.3}, {"time_epoch": 1576036800, "time": "2019-12-11 05:00", "temp_c": -0.1, "temp_f": 31.8, "is_day": 0, "condition": {"text": "Clear", "icon": "//cdn.weatherapi.com/weather/64x64/night/113.png", "code": 1000}, "wind_mph": 6.4, "wind_kph": 10.3, "wind_degree": 177, "wind_dir": "S", "pressure_mb": 1021.0, "pressure_in": 30.6, "precip_mm": 0.0, "precip_in": 0.0, "humidity": 83, "cloud": 3, "feelslike_c": -4.8, "feelslike_f": 23.4, "windchill_c": -4.8, "windchill_f": 23.4, "heatindex_c": -0.1, "heatindex_f": 31.8, "dewpoint_c": -2.7, "dewpoint_f": 27.1, "will_it_rain": 0, "chance_of_rain": "0", "will_it_snow": 0, "chance_of_snow": "0", "vis_km": 10.0, "vis_miles": 6.0, "gust_mph": 10.3, "gust_kph": 16.6}, {"time_epoch": 1576040400, "time": "2019-12-11 06:00", "temp_c": -0.1, "temp_f": 31.8, "is_day": 0, "condition": {"text": "Clear", "icon": "//cdn.weatherapi.com/weather/64x64/night/113.png", "code": 1000}, "wind_mph": 7.4, "wind_kph": 11.9, "wind_degree": 167, "wind_dir": "SSE", "pressure_mb": 1021.0, "pressure_in": 30.6, "precip_mm": 0.0, "precip_in": 0.0, "humidity": 79, "cloud": 0, "feelslike_c": -5.0, "feelslike_f": 23.0, "windchill_c": -5.0, "windchill_f": 23.0, "heatindex_c": -0.1, "heatindex_f": 31.8, "dewpoint_c": -3.2, "dewpoint_f": 26.2, "will_it_rain": 0, "chance_of_rain": "0", "will_it_snow": 0, "chance_of_snow": "0", "vis_km": 10.0, "vis_miles": 6.0, "gust_mph": 12.3, "gust_kph": 19.8}, {"time_epoch": 1576044000, "time": "2019-12-11 07:00", "temp_c": 0.4, "temp_f": 32.8, "is_day": 0, "condition": {"text": "Clear", "icon": "//cdn.weatherapi.com/weather/64x64/night/113.png", "code": 1000}, "wind_mph": 8.6, "wind_kph": 13.9, "wind_degree": 166, "wind_dir": "SSE", "pressure_mb": 1020.0, "pressure_in": 30.6, "precip_mm": 0.0, "precip_in": 0.0, "humidity": 73, "cloud": 0, "feelslike_c": -4.6, "feelslike_f": 23.7, "windchill_c": -4.6, "windchill_f": 23.7, "heatindex_c": 0.4, "heatindex_f": 32.8, "dewpoint_c": -3.8, "dewpoint_f": 25.2, "will_it_rain": 0, "chance_of_rain": "0", "will_it_snow": 0, "chance_of_snow": "0", "vis_km": 10.0, "vis_miles": 6.0, "gust_mph": 13.7, "gust_kph": 22.1}, {"time_epoch": 1576047600, "time": "2019-12-11 08:00", "temp_c": 1.0, "temp_f": 33.7, "is_day": 1, "condition": {"text": "Sunny", "icon": "//cdn.weatherapi.com/weather/64x64/day/113.png", "code": 1000}, "wind_mph": 9.9, "wind_kph": 16.0, "wind_degree": 165, "wind_dir": "SSE", "pressure_mb": 1019.0, "pressure_in": 30.6, "precip_mm": 0.0, "precip_in": 0.0, "humidity": 68, "cloud": 0, "feelslike_c": -4.3, "feelslike_f": 24.3, "windchill_c": -4.3, "windchill_f": 24.3, "heatindex_c": 1.0, "heatindex_f": 33.7, "dewpoint_c": -4.4, "dewpoint_f": 24.1, "will_it_rain": 0, "chance_of_rain": "0", "will_it_snow": 0, "chance_of_snow": "0", "vis_km": 10.0, "vis_miles": 6.0, "gust_mph": 15.1, "gust_kph": 24.4}, {"time_epoch": 1576051200, "time": "2019-12-11 09:00", "temp_c": 1.5, "temp_f": 34.7, "is_day": 1, "condition": {"text": "Sunny", "icon": "//cdn.weatherapi.com/weather/64x64/day/113.png", "code": 1000}, "wind_mph": 11.2, "wind_kph": 18.0, "wind_degree": 164, "wind_dir": "SSE", "pressure_mb": 1019.0, "pressure_in": 30.6, "precip_mm": 0.0, "precip_in": 0.0, "humidity": 62, "cloud": 0, "feelslike_c": -3.9, "feelslike_f": 25.0, "windchill_c": -3.9, "windchill_f": 25.0, "heatindex_c": 1.5, "heatindex_f": 34.7, "dewpoint_c": -5.0, "dewpoint_f": 23.0, "will_it_rain": 0, "chance_of_rain": "0", "will_it_snow": 0, "chance_of_snow": "0", "vis_km": 10.0, "vis_miles": 6.0, "gust_mph": 16.6, "gust_kph": 26.6}, {"time_epoch": 1576054800, "time": "2019-12-11 10:00", "temp_c": 2.1, "temp_f": 35.8, "is_day": 1, "condition": {"text": "Sunny", "icon": "//cdn.weatherapi.com/weather/64x64/day/113.png", "code": 1000}, "wind_mph": 11.6, "wind_kph": 18.6, "wind_degree": 163, "wind_dir": "SSE", "pressure_mb": 1018.0, "pressure_in": 30.5, "precip_mm": 0.0, "precip_in": 0.0, "humidity": 55, "cloud": 0, "feelslike_c": -3.1, "feelslike_f": 26.5, "windchill_c": -3.1, "windchill_f": 26.5, "heatindex_c": 2.1, "heatindex_f": 35.8, "dewpoint_c": -6.1, "dewpoint_f": 21.0, "will_it_rain": 0, "chance_of_rain": "0", "will_it_snow": 0, "chance_of_snow": "0", "vis_km": 10.0, "vis_miles": 6.0, "gust_mph": 16.9, "gust_kph": 27.1}, {"time_epoch": 1576058400, "time": "2019-12-11 11:00", "temp_c": 2.7, "temp_f": 36.9, "is_day": 1, "condition": {"text": "Sunny", "icon": "//cdn.weatherapi.com/weather/64x64/day/113.png", "code": 1000}, "wind_mph": 11.9, "wind_kph": 19.2, "wind_degree": 162, "wind_dir": "SSE", "pressure_mb": 1017.0, "pressure_in": 30.5, "precip_mm": 0.0, "precip_in": 0.0, "humidity": 48, "cloud": 0, "feelslike_c": -2.2, "feelslike_f": 28.0, "windchill_c": -2.2, "windchill_f": 28.0, "heatindex_c": 2.7, "heatindex_f": 36.9, "dewpoint_c": -7.3, "dewpoint_f": 18.9, "will_it_rain": 0, "chance_of_rain": "0", "will_it_snow": 0, "chance_of_snow": "0", "vis_km": 10.0, "vis_miles": 6.0, "gust_mph": 17.1, "gust_kph": 27.6}, {"time_epoch": 1576062000, "time": "2019-12-11 12:00", "temp_c": 3.3, "temp_f": 37.9, "is_day": 1, "condition": {"text": "Sunny", "icon": "//cdn.weatherapi.com/weather/64x64/day/113.png", "code": 1000}, "wind_mph": 12.3, "wind_kph": 19.8, "wind_degree": 162, "wind_dir": "SSE", "pressure_mb": 1016.0, "pressure_in": 30.5, "precip_mm": 0.0, "precip_in": 0.0, "humidity": 42, "cloud": 0, "feelslike_c": -1.4, "feelslike_f": 29.5, "windchill_c": -1.4, "windchill_f": 29.5, "heatindex_c": 3.3, "heatindex_f": 37.9, "dewpoint_c": -8.4, "dewpoint_f": 16.9, "will_it_rain": 0, "chance_of_rain": "0", "will_it_snow": 0, "chance_of_snow": "0", "vis_km": 10.0, "vis_miles": 6.0, "gust_mph": 17.4, "gust_kph": 28.1}, {"time_epoch": 1576065600, "time": "2019-12-11 13:00", "temp_c": 2.4, "temp_f": 36.3, "is_day": 1, "condition": {"text": "Sunny", "icon": "//cdn.weatherapi.com/weather/64x64/day/113.png", "code": 1000}, "wind_mph": 11.9, "wind_kph": 19.2, "wind_degree": 159, "wind_dir": "SSE", "pressure_mb": 1016.0, "pressure_in": 30.5, "precip_mm": 0.0, "precip_in": 0.0, "humidity": 46, "cloud": 0, "feelslike_c": -2.4, "feelslike_f": 27.7, "windchill_c": -2.4, "windchill_f": 27.7, "heatindex_c": 2.4, "heatindex_f": 36.3, "dewpoint_c": -8.1, "dewpoint_f": 17.4, "will_it_rain": 0, "chance_of_rain": "0", "will_it_snow": 0, "chance_of_snow": "0", "vis_km": 10.0, "vis_miles": 6.0, "gust_mph": 17.7, "gust_kph": 28.4}, {"time_epoch": 1576069200, "time": "2019-12-11 14:00", "temp_c": 1.4, "temp_f": 34.6, "is_day": 1, "condition": {"text": "Sunny", "icon": "//cdn.weatherapi.com/weather/64x64/day/113.png", "code": 1000}, "wind_mph": 11.6, "wind_kph": 18.6, "wind_degree": 157, "wind_dir": "SSE", "pressure_mb": 1015.0, "pressure_in": 30.4, "precip_mm": 0.0, "precip_in": 0.0, "humidity": 51, "cloud": 0, "feelslike_c": -3.3, "feelslike_f": 26.0, "windchill_c": -3.3, "windchill_f": 26.0, "heatindex_c": 1.4, "heatindex_f": 34.6, "dewpoint_c": -7.8, "dewpoint_f": 18.0, "will_it_rain": 0, "chance_of_rain": "0", "will_it_snow": 0, "chance_of_snow": "0", "vis_km": 10.0, "vis_miles": 6.0, "gust_mph": 17.9, "gust_kph": 28.8}, {"time_epoch": 1576072800, "time": "2019-12-11 15:00", "temp_c": 0.5, "temp_f": 32.9, "is_day": 1, "condition": {"text": "Sunny", "icon": "//cdn.weatherapi.com/weather/64x64/day/113.png", "code": 1000}, "wind_mph": 11.2, "wind_kph": 18.0, "wind_degree": 154, "wind_dir": "SSE", "pressure_mb": 1014.0, "pressure_in": 30.4, "precip_mm": 0.0, "precip_in": 0.0, "humidity": 55, "cloud": 0, "feelslike_c": -4.3, "feelslike_f": 24.3, "windchill_c": -4.3, "windchill_f": 24.3, "heatindex_c": 0.5, "heatindex_f": 32.9, "dewpoint_c": -7.5, "dewpoint_f": 18.5, "will_it_rain": 0, "chance_of_rain": "0", "will_it_snow": 0, "chance_of_snow": "0", "vis_km": 10.0, "vis_miles": 6.0, "gust_mph": 18.1, "gust_kph": 29.2}, {"time_epoch": 1576076400, "time": "2019-12-11 16:00", "temp_c": 0.2, "temp_f": 32.4, "is_day": 0, "condition": {"text": "Clear", "icon": "//cdn.weatherapi.com/weather/64x64/night/113.png", "code": 1000}, "wind_mph": 11.0, "wind_kph": 17.8, "wind_degree": 153, "wind_dir": "SSE", "pressure_mb": 1013.0, "pressure_in": 30.4, "precip_mm": 0.0, "precip_in": 0.0, "humidity": 58, "cloud": 0, "feelslike_c": -4.8, "feelslike_f": 23.4, "windchill_c": -4.8, "windchill_f": 23.4, "heatindex_c": 0.2, "heatindex_f": 32.4, "dewpoint_c": -7.2, "dewpoint_f": 19.1, "will_it_rain": 0, "chance_of_rain": "0", "will_it_snow": 0, "chance_of_snow": "0", "vis_km": 10.0, "vis_miles": 6.0, "gust_mph": 18.0, "gust_kph": 29.0}, {"time_epoch": 1576080000, "time": "2019-12-11 17:00", "temp_c": -0.0, "temp_f": 31.9, "is_day": 0, "condition": {"text": "Clear", "icon": "//cdn.weatherapi.com/weather/64x64/night/113.png", "code": 1000}, "wind_mph": 10.9, "wind_kph": 17.5, "wind_degree": 152, "wind_dir": "SSE", "pressure_mb": 1013.0, "pressure_in": 30.4, "precip_mm": 0.0, "precip_in": 0.0, "humidity": 60, "cloud": 1, "feelslike_c": -5.2, "feelslike_f": 22.6, "windchill_c": -5.2, "windchill_f": 22.6, "heatindex_c": -0.0, "heatindex_f": 31.9, "dewpoint_c": -6.8, "dewpoint_f": 19.7, "will_it_rain": 0, "chance_of_rain": "0", "will_it_snow": 0, "chance_of_snow": "0", "vis_km": 10.0, "vis_miles": 6.0, "gust_mph": 18.0, "gust_kph": 28.9}, {"time_epoch": 1576083600, "time": "2019-12-11 18:00", "temp_c": -0.3, "temp_f": 31.5, "is_day": 0, "condition": {"text": "Clear", "icon": "//cdn.weatherapi.com/weather/64x64/night/113.png", "code": 1000}, "wind_mph": 10.7, "wind_kph": 17.3, "wind_degree": 151, "wind_dir": "SSE", "pressure_mb": 1013.0, "pressure_in": 30.4, "precip_mm": 0.0, "precip_in": 0.0, "humidity": 63, "cloud": 1, "feelslike_c": -5.7, "feelslike_f": 21.7, "windchill_c": -5.7, "windchill_f": 21.7, "heatindex_c": -0.3, "heatindex_f": 31.5, "dewpoint_c": -6.5, "dewpoint_f": 20.3, "will_it_rain": 0, "chance_of_rain": "0", "will_it_snow": 0, "chance_of_snow": "0", "vis_km": 10.0, "vis_miles": 6.0, "gust_mph": 17.9, "gust_kph": 28.8}, {"time_epoch": 1576087200, "time": "2019-12-11 19:00", "temp_c": -0.4, "temp_f": 31.3, "is_day": 0, "condition": {"text": "Clear", "icon": "//cdn.weatherapi.com/weather/64x64/night/113.png", "code": 1000}, "wind_mph": 10.4, "wind_kph": 16.8, "wind_degree": 152, "wind_dir": "SSE", "pressure_mb": 1012.0, "pressure_in": 30.4, "precip_mm": 0.0, "precip_in": 0.0, "humidity": 60, "cloud": 1, "feelslike_c": -5.8, "feelslike_f": 21.6, "windchill_c": -5.8, "windchill_f": 21.6, "heatindex_c": -0.4, "heatindex_f": 31.3, "dewpoint_c": -7.1, "dewpoint_f": 19.2, "will_it_rain": 0, "chance_of_rain": "0", "will_it_snow": 0, "chance_of_snow": "0", "vis_km": 10.0, "vis_miles": 6.0, "gust_mph": 17.4, "gust_kph": 28.0}, {"time_epoch": 1576090800, "time": "2019-12-11 20:00", "temp_c": -0.4, "temp_f": 31.2, "is_day": 0, "condition": {"text": "Clear", "icon": "//cdn.weatherapi.com/weather/64x64/night/113.png", "code": 1000}, "wind_mph": 10.1, "wind_kph": 16.3, "wind_degree": 152, "wind_dir": "SSE", "pressure_mb": 1011.0, "pressure_in": 30.3, "precip_mm": 0.0, "precip_in": 0.0, "humidity": 58, "cloud": 0, "feelslike_c": -5.8, "feelslike_f": 21.5, "windchill_c": -5.8, "windchill_f": 21.5, "heatindex_c": -0.4, "heatindex_f": 31.2, "dewpoint_c": -7.7, "dewpoint_f": 18.1, "will_it_rain": 0, "chance_of_rain": "0", "will_it_snow": 0, "chance_of_snow": "0", "vis_km": 10.0, "vis_miles": 6.0, "gust_mph": 16.9, "gust_kph": 27.1}, {"time_epoch": 1576094400, "time": "2019-12-11 21:00", "temp_c": -0.5, "temp_f": 31.1, "is_day": 0, "condition": {"text": "Clear", "icon": "//cdn.weatherapi.com/weather/64x64/night/113.png", "code": 1000}, "wind_mph": 9.8, "wind_kph": 15.8, "wind_degree": 153, "wind_dir": "SSE", "pressure_mb": 1011.0, "pressure_in": 30.3, "precip_mm": 0.0, "precip_in": 0.0, "humidity": 55, "cloud": 0, "feelslike_c": -5.9, "feelslike_f": 21.4, "windchill_c": -5.9, "windchill_f": 21.4, "heatindex_c": -0.5, "heatindex_f": 31.1, "dewpoint_c": -8.3, "dewpoint_f": 17.1, "will_it_rain": 0, "chance_of_rain": "0", "will_it_snow": 0, "chance_of_snow": "0", "vis_km": 10.0, "vis_miles": 6.0, "gust_mph": 16.3, "gust_kph": 26.3}, {"time_epoch": 1576098000, "time": "2019-12-11 22:00", "temp_c": -0.5, "temp_f": 31.0, "is_day": 0, "condition": {"text": "Clear", "icon": "//cdn.weatherapi.com/weather/64x64/night/113.png", "code": 1000}, "wind_mph": 9.9, "wind_kph": 16.0, "wind_degree": 157, "wind_dir": "SSE", "pressure_mb": 1010.0, "pressure_in": 30.3, "precip_mm": 0.0, "precip_in": 0.0, "humidity": 55, "cloud": 3, "feelslike_c": -5.7, "feelslike_f": 21.7, "windchill_c": -5.7, "windchill_f": 21.7, "heatindex_c": -0.5, "heatindex_f": 31.0, "dewpoint_c": -8.3, "dewpoint_f": 17.0, "will_it_rain": 0, "chance_of_rain": "0", "will_it_snow": 0, "chance_of_snow": "0", "vis_km": 10.0, "vis_miles": 6.0, "gust_mph": 16.6, "gust_kph": 26.8}, {"time_epoch": 1576101600, "time": "2019-12-11 23:00", "temp_c": -0.6, "temp_f": 31.0, "is_day": 0, "condition": {"text": "Clear", "icon": "//cdn.weatherapi.com/weather/64x64/night/113.png", "code": 1000}, "wind_mph": 10.0, "wind_kph": 16.1, "wind_degree": 161, "wind_dir": "SSE", "pressure_mb": 1010.0, "pressure_in": 30.3, "precip_mm": 0.0, "precip_in": 0.0, "humidity": 55, "cloud": 6, "feelslike_c": -5.6, "feelslike_f": 22.0, "windchill_c": -5.6, "windchill_f": 22.0, "heatindex_c": -0.6, "heatindex_f": 31.0, "dewpoint_c": -8.4, "dewpoint_f": 16.9, "will_it_rain": 0, "chance_of_rain": "0", "will_it_snow": 0, "chance_of_snow": "0", "vis_km": 10.0, "vis_miles": 6.0, "gust_mph": 16.9, "gust_kph": 27.2}]}]}}