{"location": {"name": "Wroclaw", "region": "", "country": "Poland", "lat": 51.1, "lon": 17.03, "tz_id": "Europe/Warsaw", "localtime_epoch": 1615922825, "localtime": "2021-03-16 20:27"}, "forecast": {"forecastday": [{"date": "2020-09-27", "date_epoch": 1601164800, "day": {"maxtemp_c": 13.2, "maxtemp_f": 55.8, "mintemp_c": 8.2, "mintemp_f": 46.8, "avgtemp_c": 11.6, "avgtemp_f": 52.8, "maxwind_mph": 9.4, "maxwind_kph": 15.1, "totalprecip_mm": 0.1, "totalprecip_in": 0.0, "avgvis_km": 10.0, "avgvis_miles": 6.0, "avghumidity": 73.0, "condition": {"text": "Patchy rain possible", "icon": "//cdn.weatherapi.com/weather/64x64/day/176.png", "code": 1063}, "uv": 0.0}, "astro": {"sunrise": "05:47 AM", "sunset": "05:38 PM", "moonrise": "04:34 PM", "moonset": "12:19 AM", "moon_phase": "Waxing Gibbous", "moon_illumination": "70"}, "hour": [{"time_epoch": 1601157600, "time": "2020-09-27 00:00", "temp_c": 8.2, "temp_f": 46.8, "is_day": 0, "condition": {"text": "Partly cloudy", "icon": "//cdn.weatherapi.com/weather/64x64/night/116.png", "code": 1003}, "wind_mph": 7.8, "wind_kph": 12.6, "wind_degree": 205, "wind_dir": "SSW", "pressure_mb": 1000.0, "pressure_in": 30.0, "precip_mm": 0.0, "precip_in": 0.0, "humidity": 81, "cloud": 18, "feelslike_c": 6.0, "feelslike_f": 42.8, "windchill_c": 6.0, "windchill_f": 42.8, "heatindex_c": 8.2, "heatindex_f": 46.8, "dewpoint_c": 5.2, "dewpoint_f": 41.4, "will_it_rain": 0, "chance_of_rain": "0", "will_it_snow": 0, "chance_of_snow": "0", "vis_km": 10.0, "vis_miles": 6.0, "gust_mph": 12.3, "gust_kph": 19.8}, {"time_epoch": 1601161200, "time": "2020-09-27 01:00", "temp_c": 8.3, "temp_f": 46.9, "is_day": 0, "condition": {"text": "Partly cloudy", "icon": "//cdn.weatherapi.com/weather/64x64/night/116.png", "code": 1003}, "wind_mph": 7.3, "wind_kph": 11.8, "wind_degree": 201, "wind_dir": "SSW", "pressure_mb": 1000.0, "pressure_in": 30.0, "precip_mm": 0.0, "precip_in": 0.0, "humidity": 81, "cloud": 32, "feelslike_c": 6.2, "feelslike_f": 43.2, "windchill_c": 6.2, "windchill_f": 43.2, "heatindex_c": 8.3, "heatindex_f": 46.9, "dewpoint_c": 5.3, "dewpoint_f": 41.5, "will_it_rain": 0, "chance_of_rain": "1", "will_it_snow": 0, "chance_of_snow": "0", "vis_km": 10.0, "vis_miles": 6.0, "gust_mph": 11.5, "gust_kph": 18.5}, {"time_epoch": 1601164800, "time": "2020-09-27 02:00", "temp_c": 8.3, "temp_f": 47.0, "is_day": 0, "condition": {"text": "Partly cloudy", "icon": "//cdn.weatherapi.com/weather/64x64/night/116.png", "code": 1003}, "wind_mph": 6.8, "wind_kph": 10.9, "wind_degree": 198, "wind_dir": "SSW", "pressure_mb": 1000.0, "pressure_in": 30.0, "precip_mm": 0.0, "precip_in": 0.0, "humidity": 81, "cloud": 47, "feelslike_c": 6.5, "feelslike_f": 43.6, "windchill_c": 6.5, "windchill_f": 43.6, "heatindex_c": 8.3, "heatindex_f": 47.0, "dewpoint_c": 5.3, "dewpoint_f": 41.6, "will_it_rain": 0, "chance_of_rain": "1", "will_it_snow": 0, "chance_of_snow": "0", "vis_km": 10.0, "vis_miles": 6.0, "gust_mph": 10.7, "gust_kph": 17.2}, {"time_epoch": 1601168400, "time": "2020-09-27 03:00", "temp_c": 8.4, "temp_f": 47.1, "is_day": 0, "condition": {"text": "Partly cloudy", "icon": "//cdn.weatherapi.com/weather/64x64/night/116.png", "code": 1003}, "wind_mph": 6.3, "wind_kph": 10.1, "wind_degree": 194, "wind_dir": "SSW", "pressure_mb": 1001.0, "pressure_in": 30.0, "precip_mm": 0.0, "precip_in": 0.0, "humidity": 81, "cloud": 61, "feelslike_c": 6.7, "feelslike_f": 44.1, "windchill_c": 6.7, "windchill_f": 44.1, "heatindex_c": 8.4, "heatindex_f": 47.1, "dewpoint_c": 5.4, "dewpoint_f": 41.7, "will_it_rain": 0, "chance_of_rain": "0", "will_it_snow": 0, "chance_of_snow": "0", "vis_km": 10.0, "vis_miles": 6.0, "gust_mph": 9.8, "gust_kph": 15.8}, {"time_epoch": 1601172000, "time": "2020-09-27 04:00", "temp_c": 8.5, "temp_f": 47.4, "is_day": 0, "condition": {"text": "Partly cloudy", "icon": "//cdn.weatherapi.com/weather/64x64/night/116.png", "code": 1003}, "wind_mph": 6.0, "wind_kph": 9.6, "wind_degree": 203, "wind_dir": "SSW", "pressure_mb": 1001.0, "pressure_in": 30.0, "precip_mm": 0.0, "precip_in": 0.0, "humidity": 81, "cloud": 63, "feelslike_c": 7.0, "feelslike_f": 44.5, "windchill_c": 7.0, "windchill_f": 44.5, "heatindex_c": 8.5, "heatindex_f": 47.4, "dewpoint_c": 5.5, "dewpoint_f": 41.9, "will_it_rain": 0, "chance_of_rain": "1", "will_it_snow": 0, "chance_of_snow": "0", "vis_km": 10.0, "vis_miles": 6.0, "gust_mph": 9.2, "gust_kph": 14.8}, {"time_epoch": 1601175600, "time": "2020-09-27 05:00", "temp_c": 8.7, "temp_f": 47.6, "is_day": 0, "condition": {"text": "Cloudy", "icon": "//cdn.weatherapi.com/weather/64x64/night/119.png", "code": 1006}, "wind_mph": 5.7, "wind_kph": 9.1, "wind_degree": 211, "wind_dir": "SSW", "pressure_mb": 1001.0, "pressure_in": 30.0, "precip_mm": 0.0, "precip_in": 0.0, "humidity": 81, "cloud": 65, "feelslike_c": 7.2, "feelslike_f": 45.0, "windchill_c": 7.2, "windchill_f": 45.0, "heatindex_c": 8.7, "heatindex_f": 47.6, "dewpoint_c": 5.6, "dewpoint_f": 42.1, "will_it_rain": 0, "chance_of_rain": "2", "will_it_snow": 0, "chance_of_snow": "0", "vis_km": 10.0, "vis_miles": 6.0, "gust_mph": 8.5, "gust_kph": 13.7}, {"time_epoch": 1601179200, "time": "2020-09-27 06:00", "temp_c": 8.8, "temp_f": 47.8, "is_day": 1, "condition": {"text": "Cloudy", "icon": "//cdn.weatherapi.com/weather/64x64/day/119.png", "code": 1006}, "wind_mph": 5.4, "wind_kph": 8.6, "wind_degree": 220, "wind_dir": "SW", "pressure_mb": 1001.0, "pressure_in": 30.0, "precip_mm": 0.0, "precip_in": 0.0, "humidity": 81, "cloud": 68, "feelslike_c": 7.5, "feelslike_f": 45.5, "windchill_c": 7.5, "windchill_f": 45.5, "heatindex_c": 8.8, "heatindex_f": 47.8, "dewpoint_c": 5.7, "dewpoint_f": 42.3, "will_it_rain": 0, "chance_of_rain": "0", "will_it_snow": 0, "chance_of_snow": "0", "vis_km": 10.0, "vis_miles": 6.0, "gust_mph": 7.8, "gust_kph": 12.6}, {"time_epoch": 1601182800, "time": "2020-09-27 07:00", "temp_c": 9.5, "temp_f": 49.1, "is_day": 1, "condition": {"text": "Cloudy", "icon": "//cdn.weatherapi.com/weather/64x64/day/119.png", "code": 1006}, "wind_mph": 5.4, "wind_kph": 8.8, "wind_degree": 228, "wind_dir": "SW", "pressure_mb": 1002.0, "pressure_in": 30.0, "precip_mm": 0.0, "precip_in": 0.0, "humidity": 78, "cloud": 72, "feelslike_c": 8.3, "feelslike_f": 46.9, "windchill_c": 8.3, "windchill_f": 46.9, "heatindex_c": 9.5, "heatindex_f": 49.1, "dewpoint_c": 5.7, "dewpoint_f": 42.3, "will_it_rain": 0, "chance_of_rain": "2", "will_it_snow": 0, "chance_of_snow": "0", "vis_km": 10.0, "vis_miles": 6.0, "gust_mph": 7.5, "gust_kph": 12.1}, {"time_epoch": 1601186400, "time": "2020-09-27 08:00", "temp_c": 10.2, "temp_f": 50.4, "is_day": 1, "condition": {"text": "Partly cloudy", "icon": "//cdn.weatherapi.com/weather/64x64/day/116.png", "code": 1003}, "wind_mph": 5.5, "wind_kph": 8.9, "wind_degree": 236, "wind_dir": "WSW", "pressure_mb": 1002.0, "pressure_in": 30.1, "precip_mm": 0.0, "precip_in": 0.0, "humidity": 74, "cloud": 76, "feelslike_c": 9.0, "feelslike_f": 48.3, "windchill_c": 9.0, "windchill_f": 48.3, "heatindex_c": 10.2, "heatindex_f": 50.4, "dewpoint_c": 5.8, "dewpoint_f": 42.4, "will_it_rain": 0, "chance_of_rain": "1", "will_it_snow": 0, "chance_of_snow": "0", "vis_km": 10.0, "vis_miles": 6.0, "gust_mph": 7.2, "gust_kph": 11.6}, {"time_epoch": 1601190000, "time": "2020-09-27 09:00", "temp_c": 10.9, "temp_f": 51.6, "is_day": 1, "condition": {"text": "Partly cloudy", "icon": "//cdn.weatherapi.com/weather/64x64/day/116.png", "code": 1003}, "wind_mph": 5.6, "wind_kph": 9.0, "wind_degree": 243, "wind_dir": "WSW", "pressure_mb": 1002.0, "pressure_in": 30.1, "precip_mm": 0.0, "precip_in": 0.0, "humidity": 71, "cloud": 80, "feelslike_c": 9.8, "feelslike_f": 49.6, "windchill_c": 9.8, "windchill_f": 49.6, "heatindex_c": 10.9, "heatindex_f": 51.6, "dewpoint_c": 5.8, "dewpoint_f": 42.4, "will_it_rain": 0, "chance_of_rain": "0", "will_it_snow": 0, "chance_of_snow": "0", "vis_km": 10.0, "vis_miles": 6.0, "gust_mph": 6.9, "gust_kph": 11.2}, {"time_epoch": 1601193600, "time": "2020-09-27 10:00", "temp_c": 11.5, "temp_f": 52.7, "is_day": 1, "condition": {"text": "Partly cloudy", "icon": "//cdn.weatherapi.com/weather/64x64/day/116.png", "code": 1003}, "wind_mph": 6.4, "wind_kph": 10.3, "wind_degree": 245, "wind_dir": "WSW", "pressure_mb": 1002.0, "pressure_in": 30.1, "precip_mm": 0.0, "precip_in": 0.0, "humidity": 69, "cloud": 84, "feelslike_c": 10.4, "feelslike_f": 50.7, "windchill_c": 10.4, "windchill_f": 50.7, "heatindex_c": 11.5, "heatindex_f": 52.7, "dewpoint_c": 5.9, "dewpoint_f": 42.6, "will_it_rain": 0, "chance_of_rain": "1", "will_it_snow": 0, "chance_of_snow": "0", "vis_km": 10.0, "vis_miles": 6.0, "gust_mph": 7.7, "gust_kph": 12.4}, {"time_epoch": 1601197200, "time": "2020-09-27 11:00", "temp_c": 12.1, "temp_f": 53.8, "is_day": 1, "condition": {"text": "Overcast", "icon": "//cdn.weatherapi.com/weather/64x64/day/122.png", "code": 1009}, "wind_mph": 7.2, "wind_kph": 11.6, "wind_degree": 247, "wind_dir": "WSW", "pressure_mb": 1003.0, "pressure_in": 30.1, "precip_mm": 0.0, "precip_in": 0.0, "humidity": 67, "cloud": 89, "feelslike_c": 10.9, "feelslike_f": 51.7, "windchill_c": 10.9, "windchill_f": 51.7, "heatindex_c": 12.1, "heatindex_f": 53.8, "dewpoint_c": 6.0, "dewpoint_f": 42.8, "will_it_rain": 0, "chance_of_rain": "3", "will_it_snow": 0, "chance_of_snow": "0", "vis_km": 10.0, "vis_miles": 6.0, "gust_mph": 8.4, "gust_kph": 13.6}, {"time_epoch": 1601200800, "time": "2020-09-27 12:00", "temp_c": 12.7, "temp_f": 54.9, "is_day": 1, "condition": {"text": "Overcast", "icon": "//cdn.weatherapi.com/weather/64x64/day/122.png", "code": 1009}, "wind_mph": 8.1, "wind_kph": 13.0, "wind_degree": 248, "wind_dir": "WSW", "pressure_mb": 1003.0, "pressure_in": 30.1, "precip_mm": 0.0, "precip_in": 0.0, "humidity": 65, "cloud": 94, "feelslike_c": 11.5, "feelslike_f": 52.7, "windchill_c": 11.5, "windchill_f": 52.7, "heatindex_c": 12.7, "heatindex_f": 54.9, "dewpoint_c": 6.1, "dewpoint_f": 43.0, "will_it_rain": 0, "chance_of_rain": "0", "will_it_snow": 0, "chance_of_snow": "0", "vis_km": 10.0, "vis_miles": 6.0, "gust_mph": 9.2, "gust_kph": 14.8}, {"time_epoch": 1601204400, "time": "2020-09-27 13:00", "temp_c": 12.9, "temp_f": 55.2, "is_day": 1, "condition": {"text": "Overcast", "icon": "//cdn.weatherapi.com/weather/64x64/day/122.png", "code": 1009}, "wind_mph": 7.6, "wind_kph": 12.2, "wind_degree": 248, "wind_dir": "WSW", "pressure_mb": 1004.0, "pressure_in": 30.1, "precip_mm": 0.0, "precip_in": 0.0, "humidity": 64, "cloud": 91, "feelslike_c": 11.8, "feelslike_f": 53.2, "windchill_c": 11.8, "windchill_f": 53.2, "heatindex_c": 12.9, "heatindex_f": 55.2, "dewpoint_c": 6.2, "dewpoint_f": 43.2, "will_it_rain": 0, "chance_of_rain": "3", "will_it_snow": 0, "chance_of_snow": "0", "vis_km": 10.0, "vis_miles": 6.0, "gust_mph": 8.8, "gust_kph": 14.2}, {"time_epoch": 1601208000, "time": "2020-09-27 14:00", "temp_c": 13.0, "temp_f": 55.5, "is_day": 1, "condition": {"text": "Overcast", "icon": "//cdn.weatherapi.com/weather/64x64/day/122.png", "code": 1009}, "wind_mph": 7.2, "wind_kph": 11.5, "wind_degree": 247, "wind_dir": "WSW", "pressure_mb": 1004.0, "pressure_in": 30.1, "precip_mm": 0.03, "precip_in": 0.0, "humidity": 64, "cloud": 89, "feelslike_c": 12.1, "feelslike_f": 53.8, "windchill_c": 12.1, "windchill_f": 53.8, "heatindex_c": 13.0, "heatindex_f": 55.5, "dewpoint_c": 6.4, "dewpoint_f": 43.5, "will_it_rain": 0, "chance_of_rain": "3", "will_it_snow": 0, "chance_of_snow": "0", "vis_km": 10.0, "vis_miles": 6.0, "gust_mph": 8.4, "gust_kph": 13.6}, {"time_epoch": 1601211600, "time": "2020-09-27 15:00", "temp_c": 13.2, "temp_f": 55.8, "is_day": 1, "condition": {"text": "Overcast", "icon": "//cdn.weatherapi.com/weather/64x64/day/122.png", "code": 1009}, "wind_mph": 6.7, "wind_kph": 10.8, "wind_degree": 247, "wind_dir": "WSW", "pressure_mb": 1004.0, "pressure_in": 30.1, "precip_mm": 0.04, "precip_in": 0.0, "humidity": 64, "cloud": 86, "feelslike_c": 12.4, "feelslike_f": 54.3, "windchill_c": 12.4, "windchill_f": 54.3, "heatindex_c": 13.2, "heatindex_f": 55.8, "dewpoint_c": 6.5, "dewpoint_f": 43.7, "will_it_rain": 0, "chance_of_rain": "0", "will_it_snow": 0, "chance_of_snow": "0", "vis_km": 10.0, "vis_miles": 6.0, "gust_mph": 8.1, "gust_kph": 13.0}, {"time_epoch": 1601215200, "time": "2020-09-27 16:00", "temp_c": 12.9, "temp_f": 55.2, "is_day": 1, "condition": {"text": "Overcast", "icon": "//cdn.weatherapi.com/weather/64x64/day/122.png", "code": 1009}, "wind_mph": 7.1, "wind_kph": 11.4, "wind_degree": 238, "wind_dir": "WSW", "pressure_mb": 1005.0, "pressure_in": 30.1, "precip_mm": 0.02, "precip_in": 0.0, "humidity": 65, "cloud": 89, "feelslike_c": 11.9, "feelslike_f": 53.5, "windchill_c": 11.9, "windchill_f": 53.5, "heatindex_c": 12.9, "heatindex_f": 55.2, "dewpoint_c": 6.5, "dewpoint_f": 43.7, "will_it_rain": 0, "chance_of_rain": "3", "will_it_snow": 0, "chance_of_snow": "0", "vis_km": 10.0, "vis_miles": 6.0, "gust_mph": 9.5, "gust_kph": 15.2}, {"time_epoch": 1601218800, "time": "2020-09-27 17:00", "temp_c": 12.6, "temp_f": 54.7, "is_day": 1, "condition": {"text": "Patchy rain possible", "icon": "//cdn.weatherapi.com/weather/64x64/day/176.png", "code": 1063}, "wind_mph": 7.5, "wind_kph": 12.0, "wind_degree": 229, "wind_dir": "SW", "pressure_mb": 1005.0, "pressure_in": 30.2, "precip_mm": 0.0, "precip_in": 0.0, "humidity": 67, "cloud": 91, "feelslike_c": 11.5, "feelslike_f": 52.6, "windchill_c": 11.5, "windchill_f": 52.6, "heatindex_c": 12.6, "heatindex_f": 54.7, "dewpoint_c": 6.5, "dewpoint_f": 43.7, "will_it_rain": 0, "chance_of_rain": "21", "will_it_snow": 0, "chance_of_snow": "0", "vis_km": 10.0, "vis_miles": 6.0, "gust_mph": 10.9, "gust_kph": 17.5}, {"time_epoch": 1601222400, "time": "2020-09-27 18:00", "temp_c": 12.3, "temp_f": 54.1, "is_day": 0, "condition": {"text": "Patchy rain possible", "icon": "//cdn.weatherapi.com/weather/64x64/night/176.png", "code": 1063}, "wind_mph": 7.8, "wind_kph": 12.6, "wind_degree": 220, "wind_dir": "SW", "pressure_mb": 1006.0, "pressure_in": 30.2, "precip_mm": 0.0, "precip_in": 0.0, "humidity": 68, "cloud": 94, "feelslike_c": 11.0, "feelslike_f": 51.8, "windchill_c": 11.0, "windchill_f": 51.8, "heatindex_c": 12.3, "heatindex_f": 54.1, "dewpoint_c": 6.5, "dewpoint_f": 43.7, "will_it_rain": 0, "chance_of_rain": "0", "will_it_snow": 0, "chance_of_snow": "0", "vis_km": 10.0, "vis_miles": 6.0, "gust_mph": 12.3, "gust_kph": 19.8}, {"time_epoch": 1601226000, "time": "2020-09-27 19:00", "temp_c": 12.0, "temp_f": 53.5, "is_day": 0, "condition": {"text": "Patchy rain possible", "icon": "//cdn.weatherapi.com/weather/64x64/night/176.png", "code": 1063}, "wind_mph": 8.4, "wind_kph": 13.4, "wind_degree": 215, "wind_dir": "SW", "pressure_mb": 1006.0, "pressure_in": 30.2, "precip_mm": 0.0, "precip_in": 0.0, "humidity": 69, "cloud": 85, "feelslike_c": 10.5, "feelslike_f": 50.9, "windchill_c": 10.5, "windchill_f": 50.9, "heatindex_c": 12.0, "heatindex_f": 53.5, "dewpoint_c": 6.4, "dewpoint_f": 43.6, "will_it_rain": 0, "chance_of_rain": "21", "will_it_snow": 0, "chance_of_snow": "0", "vis_km": 10.0, "vis_miles": 6.0, "gust_mph": 13.6, "gust_kph": 21.8}, {"time_epoch": 1601229600, "time": "2020-09-27 20:00", "temp_c": 11.6, "temp_f": 52.9, "is_day": 0, "condition": {"text": "Overcast", "icon": "//cdn.weatherapi.com/weather/64x64/night/122.png", "code": 1009}, "wind_mph": 8.9, "wind_kph": 14.3, "wind_degree": 209, "wind_dir": "SSW", "pressure_mb": 1007.0, "pressure_in": 30.2, "precip_mm": 0.0, "precip_in": 0.0, "humidity": 70, "cloud": 77, "feelslike_c": 10.0, "feelslike_f": 50.0, "windchill_c": 10.0, "windchill_f": 50.0, "heatindex_c": 11.6, "heatindex_f": 52.9, "dewpoint_c": 6.4, "dewpoint_f": 43.5, "will_it_rain": 0, "chance_of_rain": "3", "will_it_snow": 0, "chance_of_snow": "0", "vis_km": 10.0, "vis_miles": 6.0, "gust_mph": 14.8, "gust_kph": 23.9}, {"time_epoch": 1601233200, "time": "2020-09-27 21:00", "temp_c": 11.3, "temp_f": 52.3, "is_day": 0, "condition": {"text": "Overcast", "icon": "//cdn.weatherapi.com/weather/64x64/night/122.png", "code": 1009}, "wind_mph": 9.4, "wind_kph": 15.1, "wind_degree": 204, "wind_dir": "SSW", "pressure_mb": 1008.0, "pressure_in": 30.2, "precip_mm": 0.0, "precip_in": 0.0, "humidity": 72, "cloud": 69, "feelslike_c": 9.5, "feelslike_f": 49.1, "windchill_c": 9.5, "windchill_f": 49.1, "heatindex_c": 11.3, "heatindex_f": 52.3, "dewpoint_c": 6.3, "dewpoint_f": 43.3, "will_it_rain": 0, "chance_of_rain": "0", "will_it_snow": 0, "chance_of_snow": "0", "vis_km": 10.0, "vis_miles": 6.0, "gust_mph": 16.1, "gust_kph": 25.9}, {"time_epoch": 1601236800, "time": "2020-09-27 22:00", "temp_c": 10.6, "temp_f": 51.1, "is_day": 0, "condition": {"text": "Overcast", "icon": "//cdn.weatherapi.com/weather/64x64/night/122.png", "code": 1009}, "wind_mph": 8.4, "wind_kph": 13.4, "wind_degree": 202, "wind_dir": "SSW", "pressure_mb": 1009.0, "pressure_in": 30.3, "precip_mm": 0.0, "precip_in": 0.0, "humidity": 75, "cloud": 50, "feelslike_c": 8.9, "feelslike_f": 48.0, "windchill_c": 8.9, "windchill_f": 48.0, "heatindex_c": 10.6, "heatindex_f": 51.1, "dewpoint_c": 6.3, "dewpoint_f": 43.3, "will_it_rain": 0, "chance_of_rain": "3", "will_it_snow": 0, "chance_of_snow": "0", "vis_km": 10.0, "vis_miles": 6.0, "gust_mph": 15.0, "gust_kph": 24.1}, {"time_epoch": 1601240400, "time": "2020-09-27 23:00", "temp_c": 9.9, "temp_f": 49.8, "is_day": 0, "condition": {"text": "Partly cloudy", "icon": "//cdn.weatherapi.com/weather/64x64/night/116.png", "code": 1003}, "wind_mph": 7.3, "wind_kph": 11.8, "wind_degree": 200, "wind_dir": "SSW", "pressure_mb": 1009.0, "pressure_in": 30.3, "precip_mm": 0.0, "precip_in": 0.0, "humidity": 78, "cloud": 30, "feelslike_c": 8.3, "feelslike_f": 46.9, "windchill_c": 8.3, "windchill_f": 46.9, "heatindex_c": 9.9, "heatindex_f": 49.8, "dewpoint_c": 6.3, "dewpoint_f": 43.3, "will_it_rain": 0, "chance_of_rain": "1", "will_it_snow": 0, "chance_of_snow": "0", "vis_km": 10.0, "vis_miles": 6.0, "gust_mph": 13.9, "gust_kph": 22.3}]}]}}